{
  "conservation_data": [
    {
      "id": "eneaf2",
      "sex": "female",
      "dateborn": "2009-07-01",
      "natal_pride": "enesikiria",
      "current_pride_association": "enesikiria",
      "current_pride_normalized": "enesikiria",
      "last_seen": "2019-10-07",
      "date_of_dispersal": "2013-11-27",
      "dead": true,
      "age_last_seen": 123,
      "date_of_death": "2020-10-30",
      "cause_of_death": "natural",
      "association": "pride",
      "is_missing": true,
      "name": "simaloi",
      "date_updated": "2024-01-04T12:06:29.090Z",
      "date_created": "2023-08-22T10:48:50.843Z"
    }
  ]
}